tempmailx/__init__.py
tempmailx/email.py
tempmailx-1.1.dist-info/METADATA
tempmailx-1.1.dist-info/WHEEL
tempmailx-1.1.dist-info/RECORD
