Metadata-Version: 2.1
Name: tempmailx
Version: 1.1
Summary: Temp email wrapper using 1secmail.com api
Project-URL: Homepage, https://github.com/Godwhitelight/tempmailx
Project-URL: Bug Tracker, https://github.com/Godwhitelight/tempmailx/issues
Author-email: godwhitelight <godwhitelightdis@gmail.com>
Classifier: License :: OSI Approved :: MIT License
Classifier: Operating System :: OS Independent
Classifier: Programming Language :: Python :: 3
Requires-Python: >=3.10
